neon_stt_plugin_polyglot/__init__.py
neon_stt_plugin_polyglot-0.0.2a4.dist-info/LICENSE.md
neon_stt_plugin_polyglot-0.0.2a4.dist-info/METADATA
neon_stt_plugin_polyglot-0.0.2a4.dist-info/WHEEL
neon_stt_plugin_polyglot-0.0.2a4.dist-info/entry_points.txt
neon_stt_plugin_polyglot-0.0.2a4.dist-info/top_level.txt
neon_stt_plugin_polyglot-0.0.2a4.dist-info/zip-safe
neon_stt_plugin_polyglot-0.0.2a4.dist-info/RECORD
